{
    "races": {
        "dragonborn": {
            "weight": 1,
            "modifiers": {
                "int": 2,
                "cha": 1
            }
        },
        "dwarf": {
            "weight": 2,
            "modifiers": {
                "con": 2
            }
        },
        "elf": {
            "weight": 3,
            "modifiers": {
                "dex": 2
            }
        },
        "human": {
            "weight": 5,
            "modifiers": {
                "str": 1,
                "dex": 1,
                "con": 1,
                "int": 1,
                "wis": 1,
                "cha": 1
            }
        }
    },
    "names": {
        "neutral": {
            "first_names": {
                "male": [
                    "neutral_male_first_1", "neutral_male_first_2", "neutral_male_first_3"
                ],
                "female": [
                    "neutral_female_first_1", "neutral_female_first_2", "neutral_female_first_3"
                ]
            },
            "last_names": [
                "neutral_last_1", "neutral_last_2", "neutral_last_3"
            ]
        },
        "dragonborn": {
            "first_names": {
                "male": [
                    "dragonborn_male_first_1", "dragonborn_male_first_2", "dragonborn_male_first_3"
                ],
                "female": [
                    "dragonborn_female_first_1", "dragonborn_female_first_2", "dragonborn_female_first_3"
                ]
            },
            "last_names": [
                "dragonborn_last_1", "dragonborn_last_2", "dragonborn_last_3"
            ]
        },
        "dwarf": {
            "first_names": {
                "male": [
                    "dwarf_male_first_1", "dwarf_male_first_2", "dwarf_male_first_3"
                ],
                "female": [
                    "dwarf_female_first_1", "dwarf_female_first_2", "dwarf_female_first_3"
                ]
            },
            "last_names": [
                "dwarf_last_1", "dwarf_last_2", "dwarf_last_3"
            ]
        },
        "elf": {
            "first_names": {
                "male": [
                    "elf_male_first_1", "elf_male_first_2", "elf_male_first_3"
                ],
                "female": [
                    "elf_female_first_1", "elf_female_first_2", "elf_female_first_3"
                ]
            },
            "last_names": [
                "elf_last_1", "elf_last_2", "elf_last_3"
            ]
        },
        "human": {
            "first_names": {
                "male": [
                    "human_male_first_1", "human_male_first_2", "human_male_first_3"
                ],
                "female": [
                    "human_female_first_1", "human_female_first_2", "human_female_first_3"
                ]
            },
            "last_names": [
                "human_last_1", "human_last_2", "human_last_3"
            ]
        }
    },
    "classes": {
        "commoner": {
            "weight": 5,
            "distribution": []
        },
        "fighter": {
            "weight": 1,
            "distribution": [
                "str", "con", "dex"
            ]
        },
        "ranger": {
            "weight": 1,
            "distribution": [
                "str", "con", "wis", "dex"
            ]
        },
        "wizard": {
            "weight": 1,
            "distribution": [
                "int", "con", "dex"
            ]
        },
        "bard": {
            "weight": 1,
            "distribution": [
                "cha", "con", "dex"
            ]
        }
    }
}